openos/__init__.py
openos-0.0.1.dist-info/METADATA
openos-0.0.1.dist-info/WHEEL
openos-0.0.1.dist-info/top_level.txt
openos-0.0.1.dist-info/RECORD
