Metadata-Version: 2.2
Name: openos
Version: 0.0.1
Summary: OpenOS is a Python interactable operating system for both human and AI agents.
Author-email: Eddy Liang <eddyliang216@gmail.com>
License: MIT
Requires-Python: >=3.10
